Metadata-Version: 2.1
Name: dictToXmlString
Version: 0.1
Summary: Формирование строки XML из словаря Dict
Home-page: https://github.com/danielmazurkin/PrivateNotik
License: UNKNOWN
Platform: UNKNOWN
